launchpanel/__init__.py
launchpanel/constants.py
launchpanel/core.py
launchpanel/create.py
launchpanel/run.py
launchpanel/run_tray.py
launchpanel/tray.py
launchpanel/utils.py
launchpanel/_resources/alert.png
launchpanel/_resources/bg.png
launchpanel/_resources/launch.png
launchpanel/_resources/launchpad.ui
launchpanel/_resources/north.qss
launchpanel/_resources/options.png
launchpanel/_resources/splash.png
launchpanel/_resources/style.qss
launchpanel/_resources/west.qss
launchpanel/_resources/wizard.png
launchpanel/_resources/wizard.qss
launchpanel/_resources/wizard_page_five.ui
launchpanel/_resources/wizard_page_four.ui
launchpanel/_resources/wizard_page_one.ui
launchpanel/_resources/wizard_page_three.ui
launchpanel/_resources/wizard_page_two.ui
launchpanel-2.0.1.dist-info/LICENSE
launchpanel-2.0.1.dist-info/METADATA
launchpanel-2.0.1.dist-info/WHEEL
launchpanel-2.0.1.dist-info/top_level.txt
launchpanel-2.0.1.dist-info/RECORD
