Metadata-Version: 2.1
Name: launchpanel
Version: 2.0.1
Summary: LaunchPanel is a simple interface designed to expose LaunchPad Actions to the user in an intuitive way.
Home-page: https://github.com/mikemalinowski/launchpad
Author: Mike Malinowski
Author-email: mike.malinowski@outlook.com
Keywords: launch launchpad pad action actions launchpanel panel
Classifier: Programming Language :: Python
Classifier: License :: OSI Approved :: MIT License
Classifier: Operating System :: OS Independent
License-File: LICENSE
Requires-Dist: qute
Requires-Dist: scribble
Requires-Dist: factories
Requires-Dist: launchpad
